pysimplicate/__init__.py
pysimplicate/_crm.py
pysimplicate/_hours.py
pysimplicate/_hrm.py
pysimplicate/_invoices.py
pysimplicate/_projects.py
pysimplicate/_sales.py
pysimplicate/_service.py
pysimplicate/simplicate.py
pysimplicate-0.10.1.dist-info/LICENSE
pysimplicate-0.10.1.dist-info/METADATA
pysimplicate-0.10.1.dist-info/WHEEL
pysimplicate-0.10.1.dist-info/top_level.txt
pysimplicate-0.10.1.dist-info/RECORD
