Metadata-Version: 2.1
Name: pysimplicate
Version: 0.10.1
Summary: Python wrapper for the Simplicate API
Home-page: https://github.com/hpharmsen/pysimplicate
Author: Hans-Peter Harmsen
Author-email: hph@oberon.nl
Classifier: Programming Language :: Python :: 3
Classifier: Programming Language :: Python :: 3.6
Classifier: Programming Language :: Python :: 3.7
Classifier: Programming Language :: Python :: 3.8
Classifier: Programming Language :: Python :: 3.9
Classifier: Operating System :: OS Independent
Requires-Python: >=3.6
License-File: LICENSE
Requires-Dist: requests
Requires-Dist: pandas
